maxcompute_tea_openapi/__init__.py
maxcompute_tea_openapi/client.py
maxcompute_tea_openapi/models.py
maxcompute_tea_openapi-1.1.0.dist-info/METADATA
maxcompute_tea_openapi-1.1.0.dist-info/WHEEL
maxcompute_tea_openapi-1.1.0.dist-info/top_level.txt
maxcompute_tea_openapi-1.1.0.dist-info/RECORD
